flask_configurator/__init__.py
flask_configurator/config.py
flask_configurator/reloader.py
flask_configurator-0.1.2.dist-info/WHEEL
flask_configurator-0.1.2.dist-info/METADATA
flask_configurator-0.1.2.dist-info/RECORD
