Metadata-Version: 2.4
Name: flask-configurator
Version: 0.1.2
Summary: Env and file based configuration for Flask
Author: Maxime Bouroumeau-Fuseau
Author-email: Maxime Bouroumeau-Fuseau <maxime.bouroumeau@gmail.com>
License-Expression: MIT
Requires-Dist: flask~=3.0
Requires-Dist: python-dotenv~=1.0
Requires-Dist: pyyaml~=6.0
Requires-Dist: watchdog~=6.0
Requires-Python: >=3.10
Project-URL: Repository, https://github.com/hyperflask/flask-configurator
